README.md
setup.cfg
setup.py
monolit_local_app/__init__.py
monolit_local_app/funces.py
monolit_local_app/server.py
monolit_local_app.egg-info/PKG-INFO
monolit_local_app.egg-info/SOURCES.txt
monolit_local_app.egg-info/dependency_links.txt
monolit_local_app.egg-info/requires.txt
monolit_local_app.egg-info/top_level.txt