Metadata-Version: 2.4
Name: monolit_local_app
Version: 2.0.1
Summary: Simple package for fast writing local sites and desktop apps, with html, css and javascript
Home-page: https://github.com/arseniylazarev7-ctrl/Monolit
Download-URL: https://github.com/arseniylazarev7-ctrl/Monolit/archive/v2.0.1.zip
Author: Ars2011
Author-email: arseniylazarev2011@yandex.ru
License: MIT
Project-URL: Documentation, https://github.com/arseniylazarev7-ctrl/Monolit/blob/main/README.md
Project-URL: Source, https://github.com/arseniylazarev7-ctrl/Monolit
Keywords: web,desktop,application,framework,local,javascript
Classifier: Intended Audience :: Developers
Classifier: Topic :: Software Development :: Build Tools
Classifier: Topic :: Software Development :: Libraries :: Application Frameworks
Classifier: Topic :: Software Development :: User Interfaces
Classifier: Topic :: Desktop Environment
Classifier: License :: OSI Approved :: MIT License
Classifier: Programming Language :: Python :: 3
Classifier: Programming Language :: Python :: 3.7
Classifier: Programming Language :: Python :: 3.8
Classifier: Programming Language :: Python :: 3.9
Classifier: Programming Language :: Python :: 3.10
Classifier: Programming Language :: Python :: 3.11
Classifier: Programming Language :: Python :: 3.12
Classifier: Operating System :: OS Independent
Requires-Python: >=3.7
Requires-Dist: flask
Dynamic: author
Dynamic: author-email
Dynamic: classifier
Dynamic: description
Dynamic: description-content-type
Dynamic: download-url
Dynamic: home-page
Dynamic: keywords
Dynamic: license
Dynamic: project-url
Dynamic: requires-dist
Dynamic: requires-python
Dynamic: summary
